{
  "nodes": [
    {
      "id": "周婷婷",
      "group": 1
    },
    {
      "id": "李军",
      "group": 1
    },
    {
      "id": "蔡莉莉",
      "group": 1
    },
    {
      "id": "陈慧",
      "group": 1
    },
    {
      "id": "许益巧",
      "group": 1
    },
    {
      "id": "王明洲",
      "group": 1
    },
    {
      "id": "郑书杏",
      "group": 1
    },
    {
      "id": "吴晓东",
      "group": 1
    },
    {
      "id": "张海波",
      "group": 1
    },
    {
      "id": "焦顺",
      "group": 1
    },
    {
      "id": "李建西",
      "group": 1
    },
    {
      "id": "郭尧提",
      "group": 1
    },
    {
      "id": "詹洪禹",
      "group": 1
    },
    {
      "id": "陈邦昌",
      "group": 1
    },
    {
      "id": "刘霸",
      "group": 1
    },
    {
      "id": "苏虹刚",
      "group": 1
    },
    {
      "id": "刘美真",
      "group": 1
    },
    {
      "id": "陈忠帅",
      "group": 1
    },
    {
      "id": "张云云",
      "group": 1
    },
    {
      "id": "林春敏",
      "group": 1
    },
    {
      "id": "朱应章",
      "group": 1
    },
    {
      "id": "赵建",
      "group": 1
    },
    {
      "id": "黄雪丹",
      "group": 1
    },
    {
      "id": "胡海宽",
      "group": 1
    },
    {
      "id": "杨红",
      "group": 1
    },
    {
      "id": "黄兴林",
      "group": 1
    },
    {
      "id": "杨学英",
      "group": 1
    },
    {
      "id": "徐明波辩称",
      "group": 1
    },
    {
      "id": "吴志强",
      "group": 1
    },
    {
      "id": "魏尧春",
      "group": 1
    },
    {
      "id": "赵德建",
      "group": 1
    },
    {
      "id": "林洁",
      "group": 1
    },
    {
      "id": "陈微微",
      "group": 1
    },
    {
      "id": "李锡伍",
      "group": 1
    },
    {
      "id": "张武",
      "group": 1
    },
    {
      "id": "金可建",
      "group": 1
    },
    {
      "id": "杨勇",
      "group": 1
    },
    {
      "id": "徐明日",
      "group": 1
    },
    {
      "id": "郑大稳",
      "group": 1
    },
    {
      "id": "胡志明",
      "group": 1
    },
    {
      "id": "陈仕晓",
      "group": 1
    },
    {
      "id": "赵义强",
      "group": 1
    },
    {
      "id": "林光谣",
      "group": 1
    },
    {
      "id": "林周松",
      "group": 1
    },
    {
      "id": "杨国忠",
      "group": 1
    },
    {
      "id": "林晓树",
      "group": 1
    },
    {
      "id": "周翔",
      "group": 1
    },
    {
      "id": "陈正波",
      "group": 1
    },
    {
      "id": "林小鹏",
      "group": 1
    },
    {
      "id": "范革军",
      "group": 1
    },
    {
      "id": "吕建明",
      "group": 1
    },
    {
      "id": "宋向阳",
      "group": 1
    },
    {
      "id": "姜永安",
      "group": 1
    },
    {
      "id": "邹坛忠",
      "group": 1
    },
    {
      "id": "胡津",
      "group": 1
    },
    {
      "id": "陈妮",
      "group": 1
    },
    {
      "id": "徐道杰",
      "group": 1
    },
    {
      "id": "胡二娃",
      "group": 1
    },
    {
      "id": "陈金喜",
      "group": 1
    },
    {
      "id": "潘国忠",
      "group": 1
    },
    {
      "id": "张希平",
      "group": 1
    },
    {
      "id": "叶德宠",
      "group": 1
    },
    {
      "id": "刘纪众",
      "group": 1
    },
    {
      "id": "王芳",
      "group": 1
    },
    {
      "id": "李小荣",
      "group": 1
    },
    {
      "id": "金春花",
      "group": 1
    },
    {
      "id": "金炳荣",
      "group": 1
    },
    {
      "id": "黄勇",
      "group": 1
    },
    {
      "id": "林德调",
      "group": 1
    },
    {
      "id": "陈佳佳",
      "group": 1
    },
    {
      "id": "黄明要",
      "group": 1
    },
    {
      "id": "温正行",
      "group": 1
    },
    {
      "id": "杨素品",
      "group": 1
    },
    {
      "id": "林奇",
      "group": 1
    },
    {
      "id": "孙乾学",
      "group": 1
    },
    {
      "id": "陈万松",
      "group": 1
    },
    {
      "id": "黄建",
      "group": 1
    },
    {
      "id": "何承刚",
      "group": 1
    },
    {
      "id": "韩裕辉",
      "group": 1
    },
    {
      "id": "林强华",
      "group": 1
    },
    {
      "id": "张善德",
      "group": 1
    },
    {
      "id": "杜小伟",
      "group": 1
    },
    {
      "id": "张柯",
      "group": 1
    },
    {
      "id": "张德杰",
      "group": 1
    },
    {
      "id": "叶伟晓",
      "group": 1
    },
    {
      "id": "邓伦斌",
      "group": 1
    },
    {
      "id": "晏伟明",
      "group": 1
    },
    {
      "id": "胡斌",
      "group": 1
    },
    {
      "id": "刘美华",
      "group": 1
    },
    {
      "id": "陈振枢",
      "group": 1
    },
    {
      "id": "张英孙",
      "group": 1
    },
    {
      "id": "陈章贵",
      "group": 1
    },
    {
      "id": "陈秉国",
      "group": 1
    },
    {
      "id": "吴建中",
      "group": 1
    },
    {
      "id": "车林",
      "group": 1
    },
    {
      "id": "徐志建",
      "group": 1
    },
    {
      "id": "陈金成",
      "group": 1
    },
    {
      "id": "章海峰",
      "group": 1
    },
    {
      "id": "包春慧",
      "group": 1
    },
    {
      "id": "陈蒙发",
      "group": 1
    },
    {
      "id": "蔡传余",
      "group": 1
    },
    {
      "id": "邱忠义",
      "group": 1
    },
    {
      "id": "刘本均",
      "group": 1
    },
    {
      "id": "杨守力",
      "group": 1
    },
    {
      "id": "胡传龙",
      "group": 1
    },
    {
      "id": "吴奎昌",
      "group": 1
    },
    {
      "id": "应建设",
      "group": 1
    },
    {
      "id": "梁君臣",
      "group": 1
    },
    {
      "id": "祁向东",
      "group": 1
    },
    {
      "id": "郭建飞",
      "group": 1
    },
    {
      "id": "包哲溪",
      "group": 1
    },
    {
      "id": "李发良",
      "group": 1
    },
    {
      "id": "夏浩静",
      "group": 1
    },
    {
      "id": "邹亮",
      "group": 1
    },
    {
      "id": "戴建开",
      "group": 1
    },
    {
      "id": "饶菊",
      "group": 1
    },
    {
      "id": "陈忠满",
      "group": 1
    },
    {
      "id": "幸奠奎",
      "group": 1
    },
    {
      "id": "叶建军",
      "group": 1
    },
    {
      "id": "何桂成",
      "group": 1
    },
    {
      "id": "周朝兴",
      "group": 1
    },
    {
      "id": "陈成伟",
      "group": 1
    },
    {
      "id": "吴景冬",
      "group": 1
    },
    {
      "id": "谢少敏",
      "group": 1
    },
    {
      "id": "陈剑",
      "group": 1
    },
    {
      "id": "邵伟",
      "group": 1
    },
    {
      "id": "董利前",
      "group": 1
    },
    {
      "id": "林成勇",
      "group": 1
    },
    {
      "id": "洪爱娟",
      "group": 1
    },
    {
      "id": "黄成斌",
      "group": 1
    },
    {
      "id": "胡志财",
      "group": 1
    },
    {
      "id": "朱永建",
      "group": 1
    },
    {
      "id": "廖晓英",
      "group": 1
    },
    {
      "id": "张云涛",
      "group": 1
    },
    {
      "id": "潘太朝",
      "group": 1
    },
    {
      "id": "吴东俊",
      "group": 1
    },
    {
      "id": "明兴",
      "group": 1
    },
    {
      "id": "游龙飞",
      "group": 1
    },
    {
      "id": "姜林",
      "group": 1
    },
    {
      "id": "方学该",
      "group": 1
    },
    {
      "id": "郑英博",
      "group": 1
    },
    {
      "id": "陈孙建",
      "group": 1
    },
    {
      "id": "陈平",
      "group": 1
    },
    {
      "id": "吴常顺",
      "group": 1
    },
    {
      "id": "金立华",
      "group": 1
    },
    {
      "id": "彭小丹",
      "group": 1
    },
    {
      "id": "郑国游",
      "group": 1
    },
    {
      "id": "廖志远",
      "group": 1
    },
    {
      "id": "洪玉钢",
      "group": 1
    },
    {
      "id": "宁钦",
      "group": 1
    },
    {
      "id": "黄光兵",
      "group": 1
    },
    {
      "id": "王明山",
      "group": 1
    },
    {
      "id": "许亮智",
      "group": 1
    },
    {
      "id": "高长富",
      "group": 1
    },
    {
      "id": "张孝检",
      "group": 1
    },
    {
      "id": "叶骏",
      "group": 1
    },
    {
      "id": "徐明波",
      "group": 1
    },
    {
      "id": "卢银杰",
      "group": 1
    },
    {
      "id": "叶洪超",
      "group": 1
    },
    {
      "id": "傅化浩",
      "group": 1
    },
    {
      "id": "余圣旺",
      "group": 1
    },
    {
      "id": "余如梅",
      "group": 1
    },
    {
      "id": "瞿元",
      "group": 1
    },
    {
      "id": "杜帅帅",
      "group": 1
    },
    {
      "id": "倪建乐",
      "group": 1
    },
    {
      "id": "吴晓峰",
      "group": 1
    },
    {
      "id": "冯建成",
      "group": 1
    },
    {
      "id": "胡洪志",
      "group": 1
    },
    {
      "id": "金长存",
      "group": 1
    },
    {
      "id": "李文铭",
      "group": 1
    },
    {
      "id": "徐伟钦",
      "group": 1
    },
    {
      "id": "舒富贵",
      "group": 1
    },
    {
      "id": "王玲",
      "group": 1
    },
    {
      "id": "王益锋",
      "group": 1
    },
    {
      "id": "叶昌盛",
      "group": 1
    },
    {
      "id": "郑祥志",
      "group": 1
    },
    {
      "id": "刘建山",
      "group": 1
    },
    {
      "id": "王霜霜",
      "group": 1
    },
    {
      "id": "胡国强",
      "group": 1
    },
    {
      "id": "王俊",
      "group": 1
    },
    {
      "id": "黎进财",
      "group": 1
    },
    {
      "id": "黄永革",
      "group": 1
    },
    {
      "id": "吴再斌",
      "group": 1
    },
    {
      "id": "满云昌",
      "group": 1
    },
    {
      "id": "肖卫",
      "group": 1
    },
    {
      "id": "谭宜继",
      "group": 1
    },
    {
      "id": "施久华",
      "group": 1
    },
    {
      "id": "王强华",
      "group": 1
    },
    {
      "id": "黄振华",
      "group": 1
    },
    {
      "id": "李恩记",
      "group": 1
    },
    {
      "id": "舒文",
      "group": 1
    },
    {
      "id": "胡永银",
      "group": 1
    },
    {
      "id": "蔡慈德",
      "group": 1
    },
    {
      "id": "颜艳艳",
      "group": 1
    },
    {
      "id": "林昌高",
      "group": 1
    },
    {
      "id": "邹启卫",
      "group": 1
    },
    {
      "id": "胡平",
      "group": 1
    },
    {
      "id": "王进",
      "group": 1
    },
    {
      "id": "梅纯冰",
      "group": 1
    },
    {
      "id": "方高钰",
      "group": 1
    },
    {
      "id": "应良宫",
      "group": 1
    },
    {
      "id": "林松鸽",
      "group": 1
    },
    {
      "id": "朱梓垚",
      "group": 1
    },
    {
      "id": "赵建余",
      "group": 1
    },
    {
      "id": "王晓龙",
      "group": 1
    },
    {
      "id": "陈世国",
      "group": 1
    },
    {
      "id": "孙约西",
      "group": 1
    },
    {
      "id": "张松光",
      "group": 1
    },
    {
      "id": "谷玉莲",
      "group": 1
    },
    {
      "id": "谭书灿",
      "group": 1
    },
    {
      "id": "陈于健",
      "group": 1
    },
    {
      "id": "唐小秋",
      "group": 1
    },
    {
      "id": "余列英",
      "group": 1
    },
    {
      "id": "林文华",
      "group": 1
    },
    {
      "id": "张自明",
      "group": 1
    },
    {
      "id": "熊义",
      "group": 1
    },
    {
      "id": "田远坤",
      "group": 1
    },
    {
      "id": "林德正",
      "group": 1
    },
    {
      "id": "潘剑",
      "group": 1
    },
    {
      "id": "牟秀彬",
      "group": 1
    },
    {
      "id": "林甲超",
      "group": 1
    },
    {
      "id": "蓝罗仕",
      "group": 1
    },
    {
      "id": "杨瑞",
      "group": 1
    },
    {
      "id": "詹小凤",
      "group": 1
    },
    {
      "id": "黄如霞",
      "group": 1
    },
    {
      "id": "屠文微",
      "group": 1
    },
    {
      "id": "吴来盛",
      "group": 1
    },
    {
      "id": "黄建乐",
      "group": 1
    },
    {
      "id": "卢孔派",
      "group": 1
    },
    {
      "id": "赵峰",
      "group": 1
    },
    {
      "id": "苏志淡",
      "group": 1
    },
    {
      "id": "郑海利",
      "group": 1
    },
    {
      "id": "陈焕艺",
      "group": 1
    },
    {
      "id": "肖荣发",
      "group": 1
    },
    {
      "id": "罗兴奎",
      "group": 1
    },
    {
      "id": "邓姣姣",
      "group": 1
    },
    {
      "id": "吴建忠",
      "group": 1
    },
    {
      "id": "张荣华",
      "group": 1
    },
    {
      "id": "陈加驹",
      "group": 1
    },
    {
      "id": "周军强",
      "group": 1
    },
    {
      "id": "郑波",
      "group": 1
    },
    {
      "id": "胡寿均",
      "group": 1
    },
    {
      "id": "周进海",
      "group": 1
    },
    {
      "id": "郭超",
      "group": 1
    },
    {
      "id": "叶加龙",
      "group": 1
    },
    {
      "id": "陈宇",
      "group": 1
    },
    {
      "id": "林苗",
      "group": 1
    },
    {
      "id": "缪丹丹",
      "group": 1
    },
    {
      "id": "郝金阳",
      "group": 1
    },
    {
      "id": "陈彩平",
      "group": 1
    },
    {
      "id": "刘祝生",
      "group": 1
    },
    {
      "id": "陈海勇",
      "group": 1
    },
    {
      "id": "王晓芬",
      "group": 1
    },
    {
      "id": "陈德锋",
      "group": 1
    },
    {
      "id": "吴小平",
      "group": 1
    },
    {
      "id": "邱波",
      "group": 1
    },
    {
      "id": "黄瑞国",
      "group": 1
    },
    {
      "id": "徐小燕",
      "group": 1
    },
    {
      "id": "高启海",
      "group": 1
    },
    {
      "id": "黄梅",
      "group": 1
    },
    {
      "id": "张远江",
      "group": 1
    },
    {
      "id": "黄锡杰",
      "group": 1
    },
    {
      "id": "刘兵",
      "group": 1
    },
    {
      "id": "黄财余",
      "group": 1
    },
    {
      "id": "张兴",
      "group": 1
    },
    {
      "id": "王小元",
      "group": 1
    },
    {
      "id": "黄志坪",
      "group": 1
    },
    {
      "id": "叶大泽",
      "group": 1
    },
    {
      "id": "黄挣意",
      "group": 1
    },
    {
      "id": "张青银",
      "group": 1
    },
    {
      "id": "章克炮",
      "group": 1
    },
    {
      "id": "应林丽",
      "group": 1
    },
    {
      "id": "陈贤钏",
      "group": 1
    },
    {
      "id": "王祥德",
      "group": 1
    },
    {
      "id": "何建峰",
      "group": 1
    },
    {
      "id": "杨飚",
      "group": 1
    },
    {
      "id": "郑鸥涨",
      "group": 1
    },
    {
      "id": "陈云波",
      "group": 1
    },
    {
      "id": "陈亦鹏",
      "group": 1
    },
    {
      "id": "苏旭钧",
      "group": 1
    },
    {
      "id": "张在盛",
      "group": 1
    },
    {
      "id": "陈启红",
      "group": 1
    },
    {
      "id": "蔡成志",
      "group": 1
    },
    {
      "id": "杨远阳",
      "group": 1
    },
    {
      "id": "金扬信",
      "group": 1
    },
    {
      "id": "吴华义",
      "group": 1
    },
    {
      "id": "缪茂起",
      "group": 1
    },
    {
      "id": "章杨英",
      "group": 1
    },
    {
      "id": "陈小平",
      "group": 1
    },
    {
      "id": "叶家平",
      "group": 1
    },
    {
      "id": "刘燕",
      "group": 1
    },
    {
      "id": "谢庆勇",
      "group": 1
    },
    {
      "id": "张立刚",
      "group": 1
    },
    {
      "id": "陈显庶",
      "group": 1
    },
    {
      "id": "黄海兵",
      "group": 1
    },
    {
      "id": "林庆权",
      "group": 1
    },
    {
      "id": "张好平",
      "group": 1
    },
    {
      "id": "饶正林",
      "group": 1
    },
    {
      "id": "邱定磊",
      "group": 1
    },
    {
      "id": "陈上海",
      "group": 1
    },
    {
      "id": "王伟州",
      "group": 1
    },
    {
      "id": "侯百康",
      "group": 1
    },
    {
      "id": "郑怀周",
      "group": 1
    },
    {
      "id": "毛传敏",
      "group": 1
    },
    {
      "id": "范玉均",
      "group": 1
    },
    {
      "id": "薛永强",
      "group": 1
    },
    {
      "id": "陈康谱",
      "group": 1
    },
    {
      "id": "朱代国",
      "group": 1
    },
    {
      "id": "罗惜盆",
      "group": 1
    },
    {
      "id": "万晓玉",
      "group": 1
    },
    {
      "id": "陈万新",
      "group": 1
    },
    {
      "id": "张宝顺",
      "group": 1
    },
    {
      "id": "杨道将",
      "group": 1
    },
    {
      "id": "王长寿",
      "group": 1
    },
    {
      "id": "胡寅熠",
      "group": 1
    },
    {
      "id": "钱凯豪",
      "group": 1
    },
    {
      "id": "李向军",
      "group": 1
    },
    {
      "id": "廖小山",
      "group": 1
    },
    {
      "id": "黄淳晨",
      "group": 1
    },
    {
      "id": "林建克",
      "group": 1
    },
    {
      "id": "邓发亮",
      "group": 1
    },
    {
      "id": "蒋业",
      "group": 1
    },
    {
      "id": "彭家强",
      "group": 1
    },
    {
      "id": "胡耀剑",
      "group": 1
    },
    {
      "id": "余蓉蓉",
      "group": 1
    },
    {
      "id": "赖登汪",
      "group": 1
    },
    {
      "id": "叶阿爱",
      "group": 1
    },
    {
      "id": "易小孩",
      "group": 1
    },
    {
      "id": "方建勇",
      "group": 1
    },
    {
      "id": "李明包",
      "group": 1
    },
    {
      "id": "陈祥金",
      "group": 1
    },
    {
      "id": "程曼曼",
      "group": 1
    },
    {
      "id": "潘林娒",
      "group": 1
    },
    {
      "id": "吴泉",
      "group": 1
    },
    {
      "id": "邵建敏",
      "group": 1
    },
    {
      "id": "徐国星",
      "group": 1
    },
    {
      "id": "姚培培",
      "group": 1
    },
    {
      "id": "张丹丹",
      "group": 1
    },
    {
      "id": "陈玉美",
      "group": 1
    },
    {
      "id": "许益都",
      "group": 1
    },
    {
      "id": "林日明",
      "group": 1
    },
    {
      "id": "刘剑",
      "group": 1
    },
    {
      "id": "侯兴锋",
      "group": 1
    },
    {
      "id": "叶月明",
      "group": 1
    },
    {
      "id": "高元超",
      "group": 1
    },
    {
      "id": "赵威",
      "group": 1
    },
    {
      "id": "叶文邦",
      "group": 1
    },
    {
      "id": "杨军",
      "group": 1
    },
    {
      "id": "朱式锋",
      "group": 1
    },
    {
      "id": "潘俊怡",
      "group": 1
    },
    {
      "id": "林冷双",
      "group": 1
    },
    {
      "id": "陈皓峰",
      "group": 1
    },
    {
      "id": "谷瑞松",
      "group": 1
    },
    {
      "id": "王占斌",
      "group": 1
    },
    {
      "id": "戴银珑",
      "group": 1
    },
    {
      "id": "徐春水",
      "group": 1
    },
    {
      "id": "潘洪兵",
      "group": 1
    },
    {
      "id": "王祁勤",
      "group": 1
    },
    {
      "id": "张空",
      "group": 1
    },
    {
      "id": "林声远",
      "group": 1
    },
    {
      "id": "段昭焕",
      "group": 1
    },
    {
      "id": "姚凯",
      "group": 1
    },
    {
      "id": "易礼强",
      "group": 1
    },
    {
      "id": "杨小林",
      "group": 1
    },
    {
      "id": "叶金荣",
      "group": 1
    },
    {
      "id": "卢多多",
      "group": 1
    },
    {
      "id": "董文龙",
      "group": 1
    },
    {
      "id": "李晓霞",
      "group": 1
    },
    {
      "id": "吴崇伟",
      "group": 1
    },
    {
      "id": "何晋焱",
      "group": 1
    },
    {
      "id": "张力",
      "group": 1
    },
    {
      "id": "倪智进",
      "group": 1
    },
    {
      "id": "洪方雄",
      "group": 1
    },
    {
      "id": "李银蕊",
      "group": 1
    },
    {
      "id": "刘阿梅",
      "group": 1
    },
    {
      "id": "袁俊",
      "group": 1
    },
    {
      "id": "刘盛军",
      "group": 1
    },
    {
      "id": "舒美仁",
      "group": 1
    },
    {
      "id": "刘红",
      "group": 1
    },
    {
      "id": "倪再银",
      "group": 1
    },
    {
      "id": "敖开洪",
      "group": 1
    },
    {
      "id": "毛晓洁",
      "group": 1
    },
    {
      "id": "郑义",
      "group": 1
    },
    {
      "id": "黄川",
      "group": 1
    },
    {
      "id": "谢连成",
      "group": 1
    },
    {
      "id": "罗华景",
      "group": 1
    },
    {
      "id": "叶春凤",
      "group": 1
    },
    {
      "id": "张自豪",
      "group": 1
    },
    {
      "id": "蒋来来",
      "group": 1
    },
    {
      "id": "戴陈利",
      "group": 1
    },
    {
      "id": "谢卫",
      "group": 1
    },
    {
      "id": "谢国兴",
      "group": 1
    },
    {
      "id": "田仁发",
      "group": 1
    },
    {
      "id": "雷丽华",
      "group": 1
    },
    {
      "id": "董加敏",
      "group": 1
    },
    {
      "id": "徐洲",
      "group": 1
    },
    {
      "id": "陈洁",
      "group": 1
    },
    {
      "id": "胡亭亭",
      "group": 1
    },
    {
      "id": "叶章华",
      "group": 1
    },
    {
      "id": "李东锋",
      "group": 1
    },
    {
      "id": "周召建",
      "group": 1
    },
    {
      "id": "赵义红",
      "group": 1
    },
    {
      "id": "韦克宁",
      "group": 1
    },
    {
      "id": "连俊",
      "group": 1
    },
    {
      "id": "杨刚",
      "group": 1
    },
    {
      "id": "连乐斌",
      "group": 1
    },
    {
      "id": "金节红",
      "group": 1
    },
    {
      "id": "谭洪胜",
      "group": 1
    },
    {
      "id": "林国富",
      "group": 1
    },
    {
      "id": "王凯",
      "group": 1
    },
    {
      "id": "林小芳",
      "group": 1
    },
    {
      "id": "张曦",
      "group": 1
    },
    {
      "id": "李耀平",
      "group": 1
    },
    {
      "id": "李哨平",
      "group": 1
    },
    {
      "id": "杨美芳",
      "group": 1
    },
    {
      "id": "陈尧波",
      "group": 1
    },
    {
      "id": "张佐波",
      "group": 1
    },
    {
      "id": "易新蓉",
      "group": 1
    },
    {
      "id": "林祥祥",
      "group": 1
    },
    {
      "id": "鲍选靖",
      "group": 1
    },
    {
      "id": "瞿毅",
      "group": 1
    },
    {
      "id": "严逍遥",
      "group": 1
    },
    {
      "id": "徐象权",
      "group": 1
    },
    {
      "id": "刘苹",
      "group": 1
    },
    {
      "id": "王成",
      "group": 1
    },
    {
      "id": "巫茂阳",
      "group": 1
    },
    {
      "id": "黄晓宽",
      "group": 1
    },
    {
      "id": "杨世聪",
      "group": 1
    },
    {
      "id": "叶盛达",
      "group": 1
    },
    {
      "id": "周航示",
      "group": 1
    },
    {
      "id": "应颂键",
      "group": 1
    },
    {
      "id": "邬智卫",
      "group": 1
    },
    {
      "id": "吴道其",
      "group": 1
    },
    {
      "id": "张小军",
      "group": 1
    },
    {
      "id": "蔡建胜",
      "group": 1
    },
    {
      "id": "王少彩",
      "group": 1
    }
  ],
  "links": [
    {
      "source": "张荣华",
      "target": "徐志建",
      "value": 40,
      "relation": "伙同"
    },
    {
      "source": "徐志建",
      "target": "张荣华",
      "value": 40,
      "relation": "是"
    },
    {
      "source": "张荣华",
      "target": "徐志建",
      "value": 40,
      "relation": "伙同"
    },
    {
      "source": "吴建中",
      "target": "李哨平",
      "value": 40,
      "relation": "交由"
    },
    {
      "source": "李哨平",
      "target": "吴建中",
      "value": 40,
      "relation": "抓获"
    },
    {
      "source": "李哨平",
      "target": "吴建中",
      "value": 40,
      "relation": "出"
    },
    {
      "source": "李哨平",
      "target": "吴建中",
      "value": 40,
      "relation": "减轻"
    },
    {
      "source": "吴建中",
      "target": "李哨平",
      "value": 40,
      "relation": "没收"
    },
    {
      "source": "吴建中",
      "target": "李哨平",
      "value": 40,
      "relation": "交由"
    },
    {
      "source": "李哨平",
      "target": "吴建中",
      "value": 40,
      "relation": "携带"
    },
    {
      "source": "李哨平",
      "target": "吴建中",
      "value": 40,
      "relation": "抓获"
    },
    {
      "source": "李哨平",
      "target": "吴建中",
      "value": 40,
      "relation": "出"
    },
    {
      "source": "潘国忠",
      "target": "黄成斌",
      "value": 40,
      "relation": "容留"
    },
    {
      "source": "林甲超",
      "target": "周翔",
      "value": 40,
      "relation": "卖"
    },
    {
      "source": "林甲超",
      "target": "周翔",
      "value": 40,
      "relation": "卖"
    },
    {
      "source": "周翔",
      "target": "潘俊怡",
      "value": 40,
      "relation": "拘役"
    },
    {
      "source": "杜小伟",
      "target": "胡斌",
      "value": 40,
      "relation": "明知"
    },
    {
      "source": "杜小伟",
      "target": "胡斌",
      "value": 40,
      "relation": "明知"
    },
    {
      "source": "胡斌",
      "target": "杜小伟",
      "value": 40,
      "relation": "提"
    },
    {
      "source": "杜小伟",
      "target": "胡斌",
      "value": 40,
      "relation": "明知"
    },
    {
      "source": "杜小伟",
      "target": "胡斌",
      "value": 40,
      "relation": "明知"
    },
    {
      "source": "刘苹",
      "target": "郑英博",
      "value": 40,
      "relation": "明知"
    },
    {
      "source": "郑英博",
      "target": "戴银珑",
      "value": 40,
      "relation": "伙同"
    },
    {
      "source": "戴银珑",
      "target": "郑英博",
      "value": 40,
      "relation": "联系"
    },
    {
      "source": "戴银珑",
      "target": "郑英博",
      "value": 40,
      "relation": "联系"
    },
    {
      "source": "戴银珑",
      "target": "刘苹",
      "value": 40,
      "relation": "并处"
    },
    {
      "source": "戴银珑",
      "target": "郑英博",
      "value": 40,
      "relation": "伙同"
    },
    {
      "source": "郑英博",
      "target": "戴银珑",
      "value": 40,
      "relation": "辩称"
    },
    {
      "source": "刘苹",
      "target": "郑英博",
      "value": 40,
      "relation": "明知"
    },
    {
      "source": "郑英博",
      "target": "戴银珑",
      "value": 40,
      "relation": "伙同"
    },
    {
      "source": "戴银珑",
      "target": "郑英博",
      "value": 40,
      "relation": "联系"
    },
    {
      "source": "戴银珑",
      "target": "郑英博",
      "value": 40,
      "relation": "联系"
    },
    {
      "source": "戴银珑",
      "target": "郑英博",
      "value": 40,
      "relation": "供"
    },
    {
      "source": "郑英博",
      "target": "戴银珑",
      "value": 40,
      "relation": "供"
    },
    {
      "source": "郑英博",
      "target": "戴银珑",
      "value": 40,
      "relation": "转给"
    },
    {
      "source": "戴银珑",
      "target": "郑英博",
      "value": 40,
      "relation": "联系"
    },
    {
      "source": "郑英博",
      "target": "戴银珑",
      "value": 40,
      "relation": "到"
    },
    {
      "source": "张宝顺",
      "target": "杨美芳",
      "value": 40,
      "relation": "联系"
    },
    {
      "source": "杨美芳",
      "target": "张宝顺",
      "value": 40,
      "relation": "交给"
    },
    {
      "source": "张宝顺",
      "target": "杨美芳",
      "value": 40,
      "relation": "联系"
    },
    {
      "source": "吴奎昌",
      "target": "范革军",
      "value": 40,
      "relation": "联系"
    },
    {
      "source": "吴奎昌",
      "target": "章海峰",
      "value": 40,
      "relation": "查获"
    },
    {
      "source": "章海峰",
      "target": "吴奎昌",
      "value": 40,
      "relation": "携带"
    },
    {
      "source": "吴奎昌",
      "target": "范革军",
      "value": 40,
      "relation": "不符"
    },
    {
      "source": "范革军",
      "target": "章海峰",
      "value": 40,
      "relation": "伙同"
    },
    {
      "source": "章海峰",
      "target": "吴奎昌",
      "value": 40,
      "relation": "确定"
    },
    {
      "source": "吴奎昌",
      "target": "范革军",
      "value": 40,
      "relation": "联系"
    },
    {
      "source": "吴奎昌",
      "target": "章海峰",
      "value": 40,
      "relation": "共计"
    },
    {
      "source": "董利前",
      "target": "刘盛军",
      "value": 40,
      "relation": "抓获"
    },
    {
      "source": "董利前",
      "target": "刘盛军",
      "value": 40,
      "relation": "转给"
    },
    {
      "source": "董利前",
      "target": "刘盛军",
      "value": 40,
      "relation": "转给"
    },
    {
      "source": "董利前",
      "target": "刘盛军",
      "value": 40,
      "relation": "抓获"
    },
    {
      "source": "陈平",
      "target": "袁俊",
      "value": 40,
      "relation": "纠集"
    },
    {
      "source": "徐小燕",
      "target": "陈平",
      "value": 40,
      "relation": "系"
    },
    {
      "source": "徐小燕",
      "target": "袁俊",
      "value": 40,
      "relation": "联系"
    },
    {
      "source": "袁俊",
      "target": "徐小燕",
      "value": 40,
      "relation": "装入"
    },
    {
      "source": "陈平",
      "target": "徐小燕",
      "value": 40,
      "relation": "抓获"
    },
    {
      "source": "朱应章",
      "target": "游龙飞",
      "value": 40,
      "relation": "平"
    },
    {
      "source": "游龙飞",
      "target": "朱应章",
      "value": 40,
      "relation": "贩卖"
    },
    {
      "source": "李耀平",
      "target": "朱应章",
      "value": 40,
      "relation": "应当"
    },
    {
      "source": "朱应章",
      "target": "游龙飞",
      "value": 40,
      "relation": "平"
    },
    {
      "source": "游龙飞",
      "target": "朱应章",
      "value": 40,
      "relation": "减轻"
    },
    {
      "source": "朱应章",
      "target": "游龙飞",
      "value": 40,
      "relation": "平"
    },
    {
      "source": "朱应章",
      "target": "游龙飞",
      "value": 40,
      "relation": "平"
    },
    {
      "source": "朱应章",
      "target": "游龙飞",
      "value": 40,
      "relation": "平"
    },
    {
      "source": "陈正波",
      "target": "吴景冬",
      "value": 40,
      "relation": "组织"
    },
    {
      "source": "陈正波",
      "target": "杨国忠",
      "value": 40,
      "relation": "联系"
    },
    {
      "source": "陈正波",
      "target": "杨国忠",
      "value": 40,
      "relation": "指使"
    },
    {
      "source": "吴景冬",
      "target": "张希平",
      "value": 40,
      "relation": "可以"
    },
    {
      "source": "陈正波",
      "target": "吴景冬",
      "value": 40,
      "relation": "判处"
    },
    {
      "source": "吴景冬",
      "target": "陈正波",
      "value": 40,
      "relation": "帮助"
    },
    {
      "source": "陈正波",
      "target": "吴景冬",
      "value": 40,
      "relation": "排除"
    },
    {
      "source": "陈正波",
      "target": "吴景冬",
      "value": 40,
      "relation": "组织"
    },
    {
      "source": "陈正波",
      "target": "杨国忠",
      "value": 40,
      "relation": "指使"
    },
    {
      "source": "杨国忠",
      "target": "陈正波",
      "value": 40,
      "relation": "主叫"
    },
    {
      "source": "杨国忠",
      "target": "陈正波",
      "value": 40,
      "relation": "主叫"
    },
    {
      "source": "杨国忠",
      "target": "陈正波",
      "value": 40,
      "relation": "所持"
    },
    {
      "source": "陈正波",
      "target": "张孝检",
      "value": 40,
      "relation": "使用"
    },
    {
      "source": "吴景冬",
      "target": "陈正波",
      "value": 40,
      "relation": "帮"
    },
    {
      "source": "陈正波",
      "target": "张希平",
      "value": 40,
      "relation": "即"
    },
    {
      "source": "吴景冬",
      "target": "陈正波",
      "value": 40,
      "relation": "帮助"
    },
    {
      "source": "陈正波",
      "target": "杨国忠",
      "value": 40,
      "relation": "拿到"
    },
    {
      "source": "杨国忠",
      "target": "张孝检",
      "value": 40,
      "relation": "无"
    },
    {
      "source": "陈彩平",
      "target": "胡国强",
      "value": 40,
      "relation": "购买"
    },
    {
      "source": "张小军",
      "target": "应林丽",
      "value": 40,
      "relation": "交给"
    },
    {
      "source": "林强华",
      "target": "赵峰",
      "value": 40,
      "relation": "谈"
    },
    {
      "source": "林强华",
      "target": "赵峰",
      "value": 40,
      "relation": "含有"
    },
    {
      "source": "冯建成",
      "target": "林强华",
      "value": 40,
      "relation": "购买"
    },
    {
      "source": "林强华",
      "target": "冯建成",
      "value": 40,
      "relation": "含有"
    },
    {
      "source": "冯建成",
      "target": "赵峰",
      "value": 40,
      "relation": "到"
    },
    {
      "source": "陈万松",
      "target": "陈万新",
      "value": 40,
      "relation": "卖"
    },
    {
      "source": "陈万松",
      "target": "陈万新",
      "value": 40,
      "relation": "卖"
    },
    {
      "source": "陈万松",
      "target": "陈万新",
      "value": 40,
      "relation": "卖"
    },
    {
      "source": "陈万松",
      "target": "陈万新",
      "value": 40,
      "relation": "卖"
    },
    {
      "source": "邹启卫",
      "target": "邵建敏",
      "value": 40,
      "relation": "卖"
    },
    {
      "source": "王霜霜",
      "target": "戴陈利",
      "value": 40,
      "relation": "帮助"
    },
    {
      "source": "戴陈利",
      "target": "王霜霜",
      "value": 40,
      "relation": "自首"
    },
    {
      "source": "戴陈利",
      "target": "王霜霜",
      "value": 40,
      "relation": "扣押"
    },
    {
      "source": "黄勇",
      "target": "黄雪丹",
      "value": 40,
      "relation": "联系"
    },
    {
      "source": "潘剑",
      "target": "黄晓宽",
      "value": 40,
      "relation": "容留"
    },
    {
      "source": "赵建",
      "target": "陈佳佳",
      "value": 40,
      "relation": "贩卖"
    },
    {
      "source": "赵建",
      "target": "陈佳佳",
      "value": 40,
      "relation": "没有"
    },
    {
      "source": "徐国星",
      "target": "潘太朝",
      "value": 40,
      "relation": "容留"
    },
    {
      "source": "徐国星",
      "target": "潘太朝",
      "value": 40,
      "relation": "容留"
    },
    {
      "source": "徐国星",
      "target": "潘太朝",
      "value": 40,
      "relation": "容留"
    },
    {
      "source": "徐国星",
      "target": "潘太朝",
      "value": 40,
      "relation": "容留"
    },
    {
      "source": "徐国星",
      "target": "潘太朝",
      "value": 40,
      "relation": "容留"
    },
    {
      "source": "徐国星",
      "target": "潘太朝",
      "value": 40,
      "relation": "容留"
    },
    {
      "source": "肖荣发",
      "target": "叶德宠",
      "value": 40,
      "relation": "收取"
    },
    {
      "source": "段昭焕",
      "target": "范玉均",
      "value": 40,
      "relation": "容留"
    },
    {
      "source": "段昭焕",
      "target": "范玉均",
      "value": 40,
      "relation": "容留"
    },
    {
      "source": "谢卫",
      "target": "李银蕊",
      "value": 40,
      "relation": "坦白"
    },
    {
      "source": "谢卫",
      "target": "李银蕊",
      "value": 40,
      "relation": "提出"
    },
    {
      "source": "陈剑",
      "target": "陈振枢",
      "value": 40,
      "relation": "贩卖"
    },
    {
      "source": "陈剑",
      "target": "陈振枢",
      "value": 40,
      "relation": "判处"
    },
    {
      "source": "陈振枢",
      "target": "陈剑",
      "value": 40,
      "relation": "购买"
    },
    {
      "source": "王明洲",
      "target": "包春慧",
      "value": 40,
      "relation": "卖"
    },
    {
      "source": "包春慧",
      "target": "王明洲",
      "value": 40,
      "relation": "如下"
    },
    {
      "source": "吴奎昌",
      "target": "何建峰",
      "value": 40,
      "relation": "贩卖"
    },
    {
      "source": "巫茂阳",
      "target": "明兴",
      "value": 40,
      "relation": "贩卖"
    },
    {
      "source": "巫茂阳",
      "target": "明兴",
      "value": 40,
      "relation": "抓获"
    },
    {
      "source": "吴道其",
      "target": "吴奎昌",
      "value": 40,
      "relation": "放置"
    },
    {
      "source": "郑国游",
      "target": "林德调",
      "value": 40,
      "relation": "容留"
    },
    {
      "source": "郑国游",
      "target": "林德调",
      "value": 40,
      "relation": "容留"
    },
    {
      "source": "郑国游",
      "target": "林德调",
      "value": 40,
      "relation": "容留"
    },
    {
      "source": "林德调",
      "target": "郑国游",
      "value": 40,
      "relation": "容留"
    },
    {
      "source": "林德调",
      "target": "郑国游",
      "value": 40,
      "relation": "容留"
    },
    {
      "source": "林德调",
      "target": "郑国游",
      "value": 40,
      "relation": "容留"
    },
    {
      "source": "吴华义",
      "target": "陈章贵",
      "value": 40,
      "relation": "容留"
    },
    {
      "source": "倪建乐",
      "target": "叶大泽",
      "value": 40,
      "relation": "联系"
    },
    {
      "source": "刘剑",
      "target": "胡寅熠",
      "value": 40,
      "relation": "联系"
    },
    {
      "source": "胡寅熠",
      "target": "刘剑",
      "value": 40,
      "relation": "转发给"
    },
    {
      "source": "倪建乐",
      "target": "应良宫",
      "value": 40,
      "relation": "联系"
    },
    {
      "source": "应良宫",
      "target": "倪建乐",
      "value": 40,
      "relation": "准备"
    },
    {
      "source": "郑祥志",
      "target": "何桂成",
      "value": 40,
      "relation": "抓获"
    },
    {
      "source": "李文铭",
      "target": "舒富贵",
      "value": 40,
      "relation": "指使"
    },
    {
      "source": "李文铭",
      "target": "舒富贵",
      "value": 40,
      "relation": "用于"
    },
    {
      "source": "舒富贵",
      "target": "张云云",
      "value": 40,
      "relation": "系"
    },
    {
      "source": "张云云",
      "target": "李文铭",
      "value": 40,
      "relation": "使用"
    },
    {
      "source": "舒富贵",
      "target": "李文铭",
      "value": 40,
      "relation": "收到"
    },
    {
      "source": "舒富贵",
      "target": "李文铭",
      "value": 40,
      "relation": "收到"
    },
    {
      "source": "陈妮",
      "target": "李文铭",
      "value": 40,
      "relation": "伙同"
    },
    {
      "source": "李文铭",
      "target": "张云云",
      "value": 40,
      "relation": "指使"
    },
    {
      "source": "张云云",
      "target": "李文铭",
      "value": 40,
      "relation": "明知"
    },
    {
      "source": "何桂成",
      "target": "郑祥志",
      "value": 40,
      "relation": "容留"
    },
    {
      "source": "何桂成",
      "target": "郑祥志",
      "value": 40,
      "relation": "容留"
    },
    {
      "source": "何桂成",
      "target": "郑祥志",
      "value": 40,
      "relation": "容留"
    },
    {
      "source": "何桂成",
      "target": "郑祥志",
      "value": 40,
      "relation": "容留"
    },
    {
      "source": "林昌高",
      "target": "王芳",
      "value": 40,
      "relation": "合伙"
    }
  ]
}